twitter.common.zookeeper-0.3.11-py2.7-nspkg.pth
twitter/common/zookeeper/__init__.py
twitter/common/zookeeper/client.py
twitter/common/zookeeper/constants.py
twitter/common/zookeeper/kazoo_client.py
twitter/common/zookeeper/named_value.py
twitter/common/zookeeper/group/__init__.py
twitter/common/zookeeper/group/group.py
twitter/common/zookeeper/group/group_base.py
twitter/common/zookeeper/group/kazoo_cli.py
twitter/common/zookeeper/group/kazoo_group.py
twitter/common/zookeeper/serverset/__init__.py
twitter/common/zookeeper/serverset/endpoint.py
twitter/common/zookeeper/serverset/serverset.py
twitter.common.zookeeper-0.3.11.dist-info/DESCRIPTION.rst
twitter.common.zookeeper-0.3.11.dist-info/METADATA
twitter.common.zookeeper-0.3.11.dist-info/RECORD
twitter.common.zookeeper-0.3.11.dist-info/WHEEL
twitter.common.zookeeper-0.3.11.dist-info/metadata.json
twitter.common.zookeeper-0.3.11.dist-info/namespace_packages.txt
twitter.common.zookeeper-0.3.11.dist-info/top_level.txt
