Metadata-Version: 2.0
Name: twitter.common.zookeeper
Version: 0.3.11
Summary: Implementations of Twitter's service discovery libraries on top of Kazoo.
Home-page: UNKNOWN
Author: UNKNOWN
Author-email: UNKNOWN
License: UNKNOWN
Platform: UNKNOWN
Requires-Dist: kazoo (==2.2.1)
Requires-Dist: thrift
Requires-Dist: twitter.common.concurrent (==0.3.11)
Requires-Dist: twitter.common.exceptions (==0.3.11)
Requires-Dist: twitter.common.lang (==0.3.11)
Requires-Dist: twitter.common.log (==0.3.11)
Requires-Dist: twitter.common.metrics (==0.3.11)
Requires-Dist: twitter.common.quantity (==0.3.11)
Requires-Dist: twitter.common.service-thrift (==0.3.11)
Provides-Extra: old
Requires-Dist: zc-zookeeper-static (==3.4.4); extra == 'old'
